demo_mcp_server/__init__.py
demo_mcp_server/__main__.py
demo_mcp_server/server.py
demo_mcp_server_jinu-0.1.0.dist-info/METADATA
demo_mcp_server_jinu-0.1.0.dist-info/WHEEL
demo_mcp_server_jinu-0.1.0.dist-info/entry_points.txt
demo_mcp_server_jinu-0.1.0.dist-info/RECORD
