Metadata-Version: 2.4
Name: demo-mcp-server-jinu
Version: 0.1.0
Summary: Demo MCP server with tools, resources, and prompts
Author: Priyabrata Nayak
License: Apache-2.0
Requires-Python: >=3.10
Requires-Dist: mcp>=1.9.4
Requires-Dist: pydantic>=2.6
